LICENSE
README.md
setup.py
vs_nb.py
vs_nb.egg-info/PKG-INFO
vs_nb.egg-info/SOURCES.txt
vs_nb.egg-info/dependency_links.txt
vs_nb.egg-info/requires.txt
vs_nb.egg-info/top_level.txt