Metadata-Version: 2.1
Name: vs-nb
Version: 0.5.0
Summary: Converts .ipynb into .py and vice-versa
Home-page: UNKNOWN
Author: James Huckle
Author-email: empty@unknown.com
License: UNKNOWN
Platform: UNKNOWN
Classifier: Programming Language :: Python :: 3
Classifier: Programming Language :: Python :: 3.9
Classifier: License :: OSI Approved :: MIT License
Classifier: Operating System :: OS Independent
Requires-Python: >=3
License-File: LICENSE
